[
  {
    "line": 2,
    "elements": [
      {
        "before": [
          {
            "result": {
              "duration": 41025100339,
              "status": "passed"
            },
            "match": {
              "location": "Hook.initializeTest()"
            }
          }
        ],
        "line": 4,
        "name": "Login with invalid credentials",
        "description": "",
        "id": "login;login-with-invalid-credentials",
        "after": [
          {
            "result": {
              "duration": 4510242744,
              "status": "passed"
            },
            "match": {
              "location": "Hook.tearDownTest(Scenario)"
            }
          }
        ],
        "type": "scenario",
        "keyword": "Scenario",
        "steps": [
          {
            "result": {
              "duration": 51072554685,
              "status": "passed"
            },
            "line": 5,
            "name": "User is in login page",
            "match": {
              "location": "LoginSteps.user_is_in_login_page()"
            },
            "keyword": "Given "
          },
          {
            "result": {
              "duration": 13781063902,
              "status": "passed"
            },
            "line": 6,
            "name": "Enter invalid email and password",
            "match": {
              "location": "LoginSteps.enter_invalid_email_and_password()"
            },
            "keyword": "When "
          },
          {
            "result": {
              "duration": 32188033,
              "status": "passed"
            },
            "line": 7,
            "name": "Error message appear",
            "match": {
              "location": "LoginSteps.error_message_appear()"
            },
            "keyword": "Then "
          }
        ]
      }
    ],
    "name": "Login",
    "description": "",
    "id": "login",
    "keyword": "Feature",
    "uri": "login.feature",
    "tags": [
      {
        "line": 1,
        "name": "@SmokeTest"
      }
    ]
  }
]